{
  "province_name": "กระบี่",
  "constituency_number": 3,
  "type": "party_list",
  "summary_by_section": {
    "1.1": 124286,
    "1.2": 94677,
    "2.1": 127060,
    "2.2": 94677,
    "2.3": 32383,
    "3.1": 90297,
    "3.2": 2,
    "3.3": 4378,
    "3.4": 94677,
    "4.1": 89432,
    "4.2": 3260,
    "4.3": 1985
  },
  "results": [
    {
      "number": 1,
      "party": "ไทยทรัพย์ทวี",
      "votes": 488
    },
    {
      "number": 2,
      "party": "เพื่อชาติไทย",
      "votes": 673
    },
    {
      "number": 3,
      "party": "ใหม่",
      "votes": 209
    },
    {
      "number": 4,
      "party": "มิติใหม่",
      "votes": 450
    },
    {
      "number": 5,
      "party": "รวมใจไทย",
      "votes": 2159
    },
    {
      "number": 6,
      "party": "รวมไทยสร้างชาติ",
      "votes": 798
    },
    {
      "number": 7,
      "party": "พลวัต",
      "votes": 100
    },
    {
      "number": 8,
      "party": "ประชาธิปไตยใหม่",
      "votes": 1258
    },
    {
      "number": 9,
      "party": "เพื่อไทย",
      "votes": 2057
    },
    {
      "number": 10,
      "party": "ทางเลือกใหม่",
      "votes": 289
    },
    {
      "number": 11,
      "party": "เศรษฐกิจ",
      "votes": 1224
    },
    {
      "number": 12,
      "party": "เสรีรวมไทย",
      "votes": 200
    },
    {
      "number": 13,
      "party": "รวมพลังประชาชน",
      "votes": 300
    },
    {
      "number": 14,
      "party": "ท้องที่ไทย",
      "votes": 35
    },
    {
      "number": 15,
      "party": "อนาคตไทย",
      "votes": 43
    },
    {
      "number": 16,
      "party": "พลังเพื่อไทย",
      "votes": 62
    },
    {
      "number": 17,
      "party": "ไทยชนะ",
      "votes": 122
    },
    {
      "number": 18,
      "party": "พลังสังคมใหม่",
      "votes": 21
    },
    {
      "number": 19,
      "party": "สังคมประชาธิปไตยไทย",
      "votes": 80
    },
    {
      "number": 20,
      "party": "ฟิวชัน",
      "votes": 17
    },
    {
      "number": 21,
      "party": "ไทรวมพลัง",
      "votes": 46
    },
    {
      "number": 22,
      "party": "ก้าวอิสระ",
      "votes": 34
    },
    {
      "number": 23,
      "party": "ปวงชนไทย",
      "votes": 56
    },
    {
      "number": 24,
      "party": "วิชชั่นใหม่",
      "votes": 82
    },
    {
      "number": 25,
      "party": "เพื่อชีวิตใหม่",
      "votes": 85
    },
    {
      "number": 26,
      "party": "คลองไทย",
      "votes": 171
    },
    {
      "number": 27,
      "party": "ประชาธิปัตย์",
      "votes": 46386
    },
    {
      "number": 28,
      "party": "ไทยก้าวหน้า",
      "votes": 87
    },
    {
      "number": 29,
      "party": "ไทยภักดี",
      "votes": 369
    },
    {
      "number": 30,
      "party": "แรงงานสร้างชาติ",
      "votes": 76
    },
    {
      "number": 31,
      "party": "ประชากรไทย",
      "votes": 83
    },
    {
      "number": 32,
      "party": "ครูไทยเพื่อประชาชน",
      "votes": 91
    },
    {
      "number": 33,
      "party": "ประชาชาติ",
      "votes": 1324
    },
    {
      "number": 34,
      "party": "สร้างอนาคตไทย",
      "votes": 107
    },
    {
      "number": 35,
      "party": "รักชาติ",
      "votes": 146
    },
    {
      "number": 36,
      "party": "ไทยพร้อม",
      "votes": 73
    },
    {
      "number": 37,
      "party": "ภูมิใจไทย",
      "votes": 13112
    },
    {
      "number": 38,
      "party": "พลังธรรมใหม่",
      "votes": 59
    },
    {
      "number": 39,
      "party": "กรีน",
      "votes": 37
    },
    {
      "number": 40,
      "party": "ไทยธรรม",
      "votes": 17
    },
    {
      "number": 41,
      "party": "แผ่นดินธรรม",
      "votes": 5
    },
    {
      "number": 42,
      "party": "กล้าธรรม",
      "votes": 487
    },
    {
      "number": 43,
      "party": "พลังประชารัฐ",
      "votes": 75
    },
    {
      "number": 44,
      "party": "โอกาสใหม่",
      "votes": 32
    },
    {
      "number": 45,
      "party": "เป็นธรรม",
      "votes": 54
    },
    {
      "number": 46,
      "party": "ประชาชน",
      "votes": 15095
    },
    {
      "number": 47,
      "party": "ประชาไทย",
      "votes": 114
    },
    {
      "number": 48,
      "party": "ไทยสร้างไทย",
      "votes": 55
    },
    {
      "number": 49,
      "party": "ไทยก้าวใหม่",
      "votes": 114
    },
    {
      "number": 50,
      "party": "ประชาอาสาชาติ",
      "votes": 9
    },
    {
      "number": 51,
      "party": "พร้อม",
      "votes": 34
    },
    {
      "number": 52,
      "party": "เครือข่ายชาวนาแห่งประเทศไทย",
      "votes": 9
    },
    {
      "number": 53,
      "party": "ไทยพิทักษ์ธรรม",
      "votes": 12
    },
    {
      "number": 54,
      "party": "ความหวังใหม่",
      "votes": 11
    },
    {
      "number": 55,
      "party": "ไทยรวมไทย",
      "votes": 20
    },
    {
      "number": 56,
      "party": "เพื่อบ้านเมือง",
      "votes": 232
    },
    {
      "number": 57,
      "party": "พลังไทยรักชาติ",
      "votes": 48
    }
  ],
  "_source_file": "/Users/killernay/Desktop/ERS2026/data/ect-pdf-clean/party_list/2. กระบี่ เขต 3 (บช).pdf",
  "_validation": {
    "vote_sum": 89432,
    "good_votes": 89432,
    "sum_diff_pct": 0.0
  }
}