{
  "province_name": "มหาสารคาม",
  "constituency_number": 4,
  "type": "constituency",
  "summary_by_section": {
    "1.1": 125931,
    "1.2": 84945,
    "2.1": 123850,
    "2.2": 84945,
    "2.3": 38905,
    "3.1": 78875,
    "3.2": 4,
    "3.3": 6066,
    "3.4": 84945,
    "4.1": 80681,
    "4.2": 2959,
    "4.3": 1305
  },
  "results": [
    {
      "number": 1,
      "name": "นายวิเชียร จงชูวณิชย์",
      "party": "ภูมิใจไทย",
      "votes": 30843
    },
    {
      "number": 6,
      "name": "นายชนินทร์ มีนาสันติรักษ์",
      "party": "กล้าธรรม",
      "votes": 21773
    },
    {
      "number": 9,
      "name": "นายสรรพภัญญู ศิริไปล์",
      "party": "เพื่อไทย",
      "votes": 15459
    },
    {
      "number": 2,
      "name": "นายวันชนะ ชัยรุ่งเรือง",
      "party": "ประชาชน",
      "votes": 11621
    },
    {
      "number": 5,
      "name": "นายเกษม สิงพร",
      "party": "รวมไทยสร้างชาติ",
      "votes": 318
    },
    {
      "number": 4,
      "name": "นายอำนาจ ทบทอบ",
      "party": "ประชาธิปไตยใหม่",
      "votes": 286
    },
    {
      "number": 7,
      "name": "นายเนตร แก้วลาด",
      "party": "ประชาธิปัตย์",
      "votes": 248
    },
    {
      "number": 8,
      "name": "นายประสงค์ กันพล",
      "party": "พลังประชารัฐ",
      "votes": 133
    }
  ],
  "_source_file": "/Users/killernay/Desktop/ERS2026/data/ect-pdf-clean/constituency/43. มหาสารคาม เขต 4.pdf",
  "_validation": {
    "vote_sum": 80681,
    "good_votes": 80681,
    "sum_diff_pct": 0.0
  }
}